mediafiletools/__init__.py
mediafiletools/common.py
mediafiletools/find_music_dupes.py
mediafiletools/movie_sort_to_df.py
mediafiletools/series_details.py
tests/__init__.py
tests/test_main.py
media_file_tools-2.1.0.dist-info/LICENSE
media_file_tools-2.1.0.dist-info/METADATA
media_file_tools-2.1.0.dist-info/WHEEL
media_file_tools-2.1.0.dist-info/top_level.txt
media_file_tools-2.1.0.dist-info/RECORD
