Metadata-Version: 2.1
Name: media-file-tools
Version: 2.1.0
Summary: Organize your digital media files
Home-page: https://github.com/saranti/media-file-tools
Author: Tom Sarantis
Classifier: Programming Language :: Python :: 3
Classifier: License :: OSI Approved :: MIT License
Classifier: Operating System :: OS Independent
Requires-Python: >=3.6
License-File: LICENSE
Requires-Dist: pandas>=2.2.2
Requires-Dist: requests>=2.32.3
Requires-Dist: beautifulsoup4>=4.12.3
Requires-Dist: tabulate>=0.9.0
Requires-Dist: tinytag>=1.10.1
Requires-Dist: Levenshtein>=0.23.0
